itk/itkMZ3MeshIOPython.py
itk/_IOMeshMZ3Python.so
itk/IOMeshMZ3Python.py
itk/Configuration/IOMeshMZ3Config.py
itk/Configuration/IOMeshMZ3_snake_case.py
itk_iomeshmz3.libs/libtbb-e046f41a.so.12.9
itk_iomeshmz3-0.1.2.dist-info/RECORD
itk_iomeshmz3-0.1.2.dist-info/WHEEL
itk_iomeshmz3-0.1.2.dist-info/METADATA
itk_iomeshmz3-0.1.2.dist-info/licenses/LICENSE
